pascua/__init__.py
pascua/_version.py
pascua/types.py
pascua/environments/__init__.py
pascua/environments/abc.py
pascua/environments/python.py
pascua-0.0.2.dist-info/LICENSE
pascua-0.0.2.dist-info/METADATA
pascua-0.0.2.dist-info/WHEEL
pascua-0.0.2.dist-info/top_level.txt
pascua-0.0.2.dist-info/RECORD
