Metadata-Version: 2.1
Name: pascua
Version: 0.0.2
Summary: Python library to perform code execution in fully isolated environments
Home-page: https://github.com/garciparedes/pascua
Author: Sergio García Prado
Author-email: sergio@garciparedes.me
License: UNKNOWN
Platform: UNKNOWN
Requires-Dist: docker (>=4.0.0)
Requires-Dist: dill (>=0.2.9)
